dora_pyrealsense/__init__.py
dora_pyrealsense/main.py
dora_pyrealsense-0.4.1.dist-info/METADATA
dora_pyrealsense-0.4.1.dist-info/WHEEL
dora_pyrealsense-0.4.1.dist-info/entry_points.txt
dora_pyrealsense-0.4.1.dist-info/top_level.txt
dora_pyrealsense-0.4.1.dist-info/RECORD
