Metadata-Version: 2.4
Name: dora-pyrealsense
Version: 0.4.1
Summary: Dora Node for capturing video with Pyrealsense
Author-email: Haixuan Xavier Tao <tao.xavier@outlook.com>
License: MIT
Requires-Python: >=3.8
Requires-Dist: dora-rs>=0.3.9
Requires-Dist: numpy<2.0.0
Requires-Dist: opencv-python>=4.1.1
Requires-Dist: pyrealsense2-macosx>=2.54.2; sys_platform == "darwin"
Requires-Dist: pyrealsense2>=2.54.2.5684; sys_platform == "linux"
Requires-Dist: pyrealsense2==2.55.1.6486; sys_platform == "windows"
